{
	"events": [
		{
			"event_id": "dialogic_024",
			"set_theme": "theme-1692638439.cfg"
		},
		{
			"character": "",
			"event_id": "dialogic_001",
			"portrait": "",
			"text": "Amanda é uma estudante do ensino médio de 17 anos. "
		},
		{
			"character": "",
			"event_id": "dialogic_001",
			"portrait": "",
			"text": "Ela é uma pessoa como as outras que usa a internet todos os dias e é muito ativa nas redes sociais."
		},
		{
			"character": "",
			"event_id": "dialogic_001",
			"portrait": "",
			"text": "Até que..."
		}
	],
	"metadata": {
		"dialogic-version": "1.5",
		"file": "timeline-1691101247.json",
		"name": "intro"
	}
}
